setup.py
t_logging/__init__.py
t_logging.egg-info/PKG-INFO
t_logging.egg-info/SOURCES.txt
t_logging.egg-info/dependency_links.txt
t_logging.egg-info/top_level.txt
t_logging.egg-info/zip-safe