Metadata-Version: 1.0
Name: t-logging
Version: 0.1
Summary: T python logging library
Home-page: https://gitlab.com/ddmello/lib/python/threads_logging.git
Author: Darrin D'Mello
Author-email: darrin.dmello@gmail.com
License: MIT
Platform: UNKNOWN
